Metadata-Version: 2.4
Name: buildtogether
Version: 0.2.1
Summary: A collaborative project management tool for AI and software development teams with sprint tracking, task management, and issue resolution features
Home-page: https://github.com/markoinla/buildtogether
Author: Marko Stankovic
Author-email: m@marko.la
Classifier: Development Status :: 3 - Alpha
Classifier: Intended Audience :: Developers
Classifier: License :: OSI Approved :: MIT License
Classifier: Programming Language :: Python :: 3
Classifier: Programming Language :: Python :: 3.7
Classifier: Programming Language :: Python :: 3.8
Classifier: Programming Language :: Python :: 3.9
Classifier: Programming Language :: Python :: 3.10
Requires-Python: >=3.7
Requires-Dist: Flask>=3.0.0
Requires-Dist: SQLAlchemy>=2.0.20
Requires-Dist: Flask-SQLAlchemy>=3.1.0
Requires-Dist: Flask-Migrate>=4.0.0
Requires-Dist: Flask-WTF>=1.1.0
Requires-Dist: WTForms>=3.0.0
Requires-Dist: python-dotenv>=1.0.0
Requires-Dist: flask-cors>=4.0.0
Requires-Dist: markdown>=3.7.0
Requires-Dist: bleach>=6.2.0
Requires-Dist: markupsafe>=3.0.0
Requires-Dist: httpx>=0.24.0
Requires-Dist: marshmallow>=3.20.0
Requires-Dist: pydantic>=2.0.0
Requires-Dist: pytest>=7.4.0
Dynamic: author
Dynamic: author-email
Dynamic: classifier
Dynamic: description
Dynamic: description-content-type
Dynamic: home-page
Dynamic: requires-dist
Dynamic: requires-python
Dynamic: summary
